topsis_dhruv_102303645/__init__.py
topsis_dhruv_102303645/topsis_code.py
topsis_dhruv_102303645-1.0.3.dist-info/licenses/LICENCE.txt
topsis_dhruv_102303645-1.0.3.dist-info/METADATA
topsis_dhruv_102303645-1.0.3.dist-info/WHEEL
topsis_dhruv_102303645-1.0.3.dist-info/entry_points.txt
topsis_dhruv_102303645-1.0.3.dist-info/top_level.txt
topsis_dhruv_102303645-1.0.3.dist-info/RECORD
