Metadata-Version: 2.4
Name: topsis-dhruv-102303645
Version: 1.0.3
Summary: TOPSIS command line tool
Author: Dhruv
Author-email: dkamboj_be23@thapar.edu
Requires-Python: >=3.7
License-File: LICENCE.txt
Requires-Dist: numpy
Requires-Dist: pandas
Dynamic: author
Dynamic: author-email
Dynamic: description
Dynamic: description-content-type
Dynamic: license-file
Dynamic: requires-dist
Dynamic: requires-python
Dynamic: summary
